gradify.py
gradify-1.0.0.dist-info/licenses/LICENSE.txt
gradify-1.0.0.dist-info/METADATA
gradify-1.0.0.dist-info/WHEEL
gradify-1.0.0.dist-info/top_level.txt
gradify-1.0.0.dist-info/RECORD
